{
  "language_preference": "english_primary",
  "categories": {
    "tech": {
      "priority": "high",
      "sources": [
        { "name": "MIT Technology Review", "url": "https://www.technologyreview.com", "type": "web" },
        { "name": "Wired", "url": "https://www.wired.com", "type": "web" },
        { "name": "Ars Technica", "url": "https://arstechnica.com", "type": "web" },
        { "name": "The Verge", "url": "https://www.theverge.com", "type": "web" },
        { "name": "Hacker News", "url": "https://news.ycombinator.com", "type": "web" }
      ]
    },
    "finance": {
      "priority": "high",
      "sources": [
        { "name": "Bloomberg", "url": "https://www.bloomberg.com", "type": "web" },
        { "name": "Financial Times", "url": "https://www.ft.com", "type": "web" },
        { "name": "The Economist", "url": "https://www.economist.com", "type": "web" },
        { "name": "Reuters", "url": "https://www.reuters.com", "type": "web" }
      ]
    },
    "startups": {
      "priority": "medium",
      "sources": [
        { "name": "TechCrunch", "url": "https://techcrunch.com", "type": "web" },
        { "name": "Crunchbase News", "url": "https://news.crunchbase.com", "type": "web" },
        { "name": "Y Combinator Blog", "url": "https://www.ycombinator.com/blog", "type": "web" }
      ]
    },
    "life_science": {
      "priority": "medium",
      "sources": [
        { "name": "Nature News", "url": "https://www.nature.com/news", "type": "web" },
        { "name": "STAT News", "url": "https://www.statnews.com", "type": "web" },
        { "name": "Science Daily", "url": "https://www.sciencedaily.com", "type": "web" }
      ]
    },
    "macro": {
      "priority": "low",
      "sources": [
        { "name": "Foreign Affairs", "url": "https://www.foreignaffairs.com", "type": "web" },
        { "name": "The Atlantic", "url": "https://www.theatlantic.com", "type": "web" }
      ]
    }
  },
  "slack": {
    "enabled": true,
    "channel": "#daily-news"
  }
}
